torchhk/__init__.py
torchhk/rm.py
torchhk/transform.py
torchhk/datasets/__init__.py
torchhk/datasets/base.py
torchhk/datasets/cifar_corrupt.py
torchhk/datasets/cifar_unsup.py
torchhk/datasets/mnistm.py
torchhk/datasets/tinyimagenet.py
torchhk/vis/__init__.py
torchhk/vis/_base.py
torchhk/vis/_feature.py
torchhk/vis/_model.py
torchhk-0.86.14.dist-info/LICENSE
torchhk-0.86.14.dist-info/METADATA
torchhk-0.86.14.dist-info/WHEEL
torchhk-0.86.14.dist-info/top_level.txt
torchhk-0.86.14.dist-info/RECORD
