Metadata-Version: 2.1
Name: torchhk
Version: 0.86.14
Summary: Custom utils for PyTorch
Home-page: https://github.com/HarryK24/pytorch-custom-utils
Author: Harry Kim <24k.harry@gmail.com>
License: MIT
Platform: UNKNOWN
Classifier: Development Status :: 4 - Beta
Classifier: Intended Audience :: Developers
Classifier: Topic :: Scientific/Engineering :: Artificial Intelligence
Classifier: Topic :: Scientific/Engineering :: Visualization
Classifier: License :: OSI Approved :: MIT License
Classifier: Programming Language :: Python :: 3.6
Classifier: Operating System :: OS Independent
Requires-Python: >=3
Requires-Dist: plotly
